transkribus_hf/__init__.py
transkribus_hf/__version__.py
transkribus_hf/cli.py
transkribus_hf/converter.py
transkribus_hf/exporters.py
transkribus_hf/parser.py
transkribus_hf-0.1.0.dist-info/licenses/LICENSE
transkribus_hf-0.1.0.dist-info/METADATA
transkribus_hf-0.1.0.dist-info/WHEEL
transkribus_hf-0.1.0.dist-info/entry_points.txt
transkribus_hf-0.1.0.dist-info/top_level.txt
transkribus_hf-0.1.0.dist-info/RECORD
