Metadata-Version: 2.4
Name: transkribus-hf
Version: 0.1.0
Summary: Convert Transkribus ZIP files to HuggingFace datasets
Home-page: https://github.com/wjbmattingly/transkribus-hf
Author: wjbmattingly
Author-email: wjbmattingly@gmail.com
Classifier: Development Status :: 3 - Alpha
Classifier: Intended Audience :: Developers
Classifier: License :: OSI Approved :: MIT License
Classifier: Operating System :: OS Independent
Classifier: Programming Language :: Python :: 3
Classifier: Programming Language :: Python :: 3.8
Classifier: Programming Language :: Python :: 3.9
Classifier: Programming Language :: Python :: 3.10
Classifier: Programming Language :: Python :: 3.11
Requires-Python: >=3.8
License-File: LICENSE
Requires-Dist: datasets>=2.0.0
Requires-Dist: huggingface_hub>=0.15.0
Requires-Dist: Pillow>=9.0.0
Requires-Dist: lxml>=4.6.0
Requires-Dist: numpy>=1.21.0
Requires-Dist: tqdm>=4.62.0
Requires-Dist: chardet>=4.0.0
Provides-Extra: dev
Requires-Dist: pytest>=6.0; extra == "dev"
Requires-Dist: black>=22.0; extra == "dev"
Requires-Dist: flake8>=4.0; extra == "dev"
Requires-Dist: mypy>=0.910; extra == "dev"
Dynamic: author
Dynamic: author-email
Dynamic: classifier
Dynamic: description
Dynamic: description-content-type
Dynamic: home-page
Dynamic: license-file
Dynamic: provides-extra
Dynamic: requires-dist
Dynamic: requires-python
Dynamic: summary
